scum_programmer/main.py
scum_programmer/programmer/__init__.py
scum_programmer/programmer/hdlc.py
scum_programmer/programmer/scum.py
scum_programmer/programmer/serial.py
scum_programmer/tests/__init__.py
scum_programmer/tests/test_main.py
scum_programmer-0.2.2.dist-info/METADATA
scum_programmer-0.2.2.dist-info/WHEEL
scum_programmer-0.2.2.dist-info/entry_points.txt
scum_programmer-0.2.2.dist-info/licenses/LICENSE.txt
scum_programmer-0.2.2.dist-info/RECORD
