Metadata-Version: 2.4
Name: scum-programmer
Version: 0.2.2
Summary: SCuM programmer script.
Project-URL: Homepage, https://github.com/PisterLab/scum-sdk
Project-URL: Bug Tracker, https://github.com/PisterLab/scum-sdk/issues
Author-email: Alexandre Abadie <alexandre.abadie@inria.fr>
License: BSD
License-File: LICENSE.txt
Classifier: License :: OSI Approved :: BSD License
Classifier: Operating System :: MacOS
Classifier: Operating System :: Microsoft :: Windows
Classifier: Operating System :: POSIX :: Linux
Classifier: Programming Language :: Python :: 3
Requires-Python: >=3.7
Requires-Dist: click>=8.1.7
Requires-Dist: pyserial>=3.5
Requires-Dist: rich>=14.0.0
Requires-Dist: tqdm>=4.66.5
